chartspy/__init__.py
chartspy/base.py
chartspy/charts.py
chartspy/echarts.py
chartspy/g2plot.py
chartspy/highcharts.py
chartspy/klinecharts.py
chartspy/tabulator.py
chartspy/express/__init__.py
chartspy/express/echarts.py
chartspy/express/g2plot.py
chartspy/express/highcharts.py
chartspy-2.2.7.dist-info/licenses/LICENSE
chartspy-2.2.7.dist-info/METADATA
chartspy-2.2.7.dist-info/WHEEL
chartspy-2.2.7.dist-info/top_level.txt
chartspy-2.2.7.dist-info/RECORD
