Metadata-Version: 2.4
Name: chartspy
Version: 2.2.7
Summary: echarts g2plot klinechart highcharts tabulator python wrapper
Home-page: https://chartspy.icopy.site/
Author: yiliuyan
Author-email: yiliuyan161@126.com
Maintainer: yiliuyan
Maintainer-email: yiliuyan161@126.com
Keywords: echarts g2plot klinechart highcharts tabulator python
Platform: all
Classifier: Programming Language :: Python
Classifier: License :: OSI Approved :: MIT License
Classifier: Operating System :: OS Independent
Classifier: Programming Language :: Python :: 3.7
Classifier: Programming Language :: Python :: 3.8
Classifier: Programming Language :: Python :: 3.9
Classifier: Programming Language :: Python :: 3.10
Classifier: Programming Language :: Python :: 3.11
Classifier: Programming Language :: Python :: 3.12
License-File: LICENSE
Requires-Dist: pandas
Requires-Dist: numpy
Dynamic: author
Dynamic: author-email
Dynamic: classifier
Dynamic: description-content-type
Dynamic: home-page
Dynamic: keywords
Dynamic: license-file
Dynamic: maintainer
Dynamic: maintainer-email
Dynamic: platform
Dynamic: requires-dist
Dynamic: summary
